{
  "$schema": "https://raw.githubusercontent.com/martinring/tmlanguage/master/tmlanguage.json",
  "name": "Rust",
  "fileTypes": [
    "rs"
  ],
  "scopeName": "source.rust",
  "patterns": [
    {
      "comment": "documentation comments",
      "name": "comment.line.documentation.rust",
      "match": "^\\s*///.*"
    },
    {
      "comment": "line comments",
      "name": "comment.line.double-slash.rust",
      "match": "^\\s*//.*"
    },
    {
      "comment": "control flow keywords",
      "name": "keyword.control.rust",
      "match": "\\b(abstract|as|async|await|become|box|break|const|continue|do|dyn|else|enum|extern|false|final|for|if|impl|in|let|loop|macro|match|mod|move|override|priv|pub|ref|return|static|struct|trait|true|try|type|typeof|union|unsafe|unsized|use|virtual|where|while|yield)\\b"
    },
    {
      "comment": "fn",
      "name": "keyword.control.fn.rust",
      "match": "\\bfn\\b"
    },
    {
      "comment": "crate",
      "name": "keyword.other.crate.rust",
      "match": "\\bcrate\\b"
    },
    {
      "comment": "mut",
      "name": "keyword.other.mut.rust",
      "match": "\\bmut\\b"
    },
    {
      "comment": "super",
      "name": "keyword.other.super.rust",
      "match": "\\bsuper\\b"
    },
    {
      "comment": "namespace operator (::)",
      "name": "keyword.operator.namespace.rust",
      "match": "::"
    },
    {
      "comment": "double-quoted strings",
      "name": "string.quoted.double.rust",
      "begin": "\"",
      "beginCaptures": {
        "0": {
          "name": "punctuation.definition.string.begin.rust"
        }
      },
      "end": "\"",
      "endCaptures": {
        "0": {
          "name": "punctuation.definition.string.end.rust"
        }
      }
    },
    {
      "comment": "characters",
      "name": "string.quoted.single.char.rust",
      "begin": "'",
      "beginCaptures": {
        "0": {
          "name": "punctuation.definition.char.begin.rust"
        }
      },
      "end": "'",
      "endCaptures": {
        "0": {
          "name": "punctuation.definition.char.end.rust"
        }
      }
    },
    {
      "comment": "self",
      "name": "variable.language.self.rust",
      "match": "\\b[Ss]elf\\b"
    }
  ],
  "repository": null
}